{
    "id": 867,
    "name": "Number of objects generated by the Combstruct grammar defined in the Maple program. See the link for the grammar specification",
    "description": "Number of objects generated by the Combstruct grammar defined in the Maple program. See the link for the grammar specification",
    "specification": "{B = Sequence(S), C = Prod(Z,B), S =Set(C,1 <= card)}",
    "labeled": false,
    "symbol": "S",
    "terms": [
        0,
        1,
        2,
        5,
        16,
        56,
        217,
        876,
        3686,
        15903,
        70103,
        314042,
        1426076,
        6548060,
        30352695,
        141837086,
        667469159,
        3160370217,
        15045244375,
        71970393570,
        345766441537
    ],
    "references": [
        "EIS A052891"
    ]
}