{
    "id": 680,
    "name": "A simple context-free grammar in a labeled universe: a(n) = A052743(n)-A052723(n), n>1",
    "description": "A simple context-free grammar in a labeled universe: a(n) = A052743(n)-A052723(n), n>1",
    "specification": "{B = Prod(Z,C), C =Union(B,S,Z), S = Prod(B,B)}",
    "labeled": true,
    "symbol": "S",
    "terms": [
        0,
        0,
        0,
        0,
        24,
        240,
        2160,
        30240,
        524160,
        9434880,
        188697600,
        4311014400,
        108254361600,
        2939153817600,
        86568043161600,
        2753962219008000,
        93838712647680000,
        3409619685728256000,
        131735241369059328000,
        5392770591324340224000,
        233106073011436584960000
    ],
    "references": [
        "EIS A052724"
    ],
    "gf": "-(_x^2+1/2-1/2*_x-1/2*(-4*_x^3+_x^2-2*_x+1)^(1/2)+1/2*(-1+_x+(-4*_x^3+_x^2-2*_x+1)^(1/2))/_x)/_x",
    "rec": "{(4*_n^5+38*_n^4+120*_n^3+130*_n^2-4*_n-48)*_f(_n)+(-5*_n^4-52*_n^3-193*_n^2-302*_n-168)*_f(_n+1)+(3*_n^3+29*_n^2+92*_n+96)*_f(_n+2)+(-3*_n^2-25*_n-52)*_f(_n+3)+(_n+6)*_f(_n+4), _f(0) = 0, _f(1) = 0, _f(2) = 0, _f(3) =0, _f(4) = 24, _f(5) = 240}",
    "equiv": "-1/2/Pi^(1/2)/RootOf(4*_Z^3-_Z^2+2*_Z-1,.432040800333096)*(1/2*(12*RootOf(4*_Z^3-_Z^2+2*_Z-1,.432040800333096)^3-2*RootOf(4*_Z^3-_Z^2+2*_Z-1,.432040800333096)^2+2*RootOf(4*_Z^3-_Z^2+2*_Z-1,.432040800333096))^(1/2)-1/2/RootOf(4*_Z^3-_Z^2+2*_Z-1,.432040800333096)*(12*RootOf(4*_Z^3-_Z^2+2*_Z-1,.432040800333096)^3-2*RootOf(4*_Z^3-_Z^2+2*_Z-1,.432040800333096)^2+2*RootOf(4*_Z^3-_Z^2+2*_Z-1,.432040800333096))^(1/2))*(1/_n)^(3/2)*(4*RootOf(4*_Z^3-_Z^2+2*_Z-1,.432040800333096)^2-RootOf(4*_Z^3-_Z^2+2*_Z-1,.432040800333096)+2)^(-ln(exp(-_n)))"
}