{
    "id": 660,
    "name": "Expansion of 2*x^2/(1 - 2*x - 2*x^2 + sqrt(1 - 4*x - 4*x^2))",
    "description": "Expansion of 2*x^2/(1 - 2*x - 2*x^2 + sqrt(1 - 4*x - 4*x^2))",
    "specification": "{B = Union(S,C,Z), C = Prod(S,Z), S = Prod(B,B)}",
    "labeled": false,
    "symbol": "S",
    "terms": [
        0,
        0,
        1,
        2,
        7,
        24,
        89,
        342,
        1355,
        5492,
        22669,
        94962,
        402703,
        1725424,
        7458065,
        32482798,
        142414867,
        628037612,
        2783922197,
        12397342698,
        55436525591
    ],
    "references": [
        "EIS A052705"
    ],
    "gf": "-1/2*(2*_x^2+(-4*_x^2-4*_x+1)^(1/2)+2*_x-1)/(_x^2+2*_x+1)",
    "rec": "{(4*_n+4)*_f(_n)+(10+8*_n)*_f(_n+1)+(3*_n+2)*_f(_n+2)+(-_n-3)*_f(_n+3), _f(0) = 0, _f(1) = 0, _f(2) = 1, _f(3) = 2}",
    "equiv": "1/4/Pi^(1/2)*(8*(1/2*2^(1/2)-1/2)^2+2*2^(1/2)-2)^(1/2)/((1/2*2^(1/2)-1/2)^2+2^(1/2))*(1/_n)^(3/2)*exp(-_n)^(-ln(2)+ln(2^(1/2)-1))"
}