{
    "id": 694,
    "name": "A simple context-free grammar in a labeled universe",
    "description": "A simple context-free grammar in a labeled universe",
    "specification": "{B = Union(S,Z,C),C = Prod(S,S), S = Prod(B,B)}",
    "labeled": true,
    "symbol": "S",
    "terms": [
        0,
        0,
        2,
        12,
        120,
        1920,
        40320,
        1028160,
        30965760,
        1077753600,
        42551308800,
        1878484608000,
        91686654259200,
        4902558383923200,
        284994551761920000,
        17895345882365952000,
        1207064057173438464000,
        87041570211234422784000,
        6682058059023653289984000,
        544097659829475380428800000,
        46838339233955282209996800000
    ],
    "references": [
        "EIS A052738"
    ],
    "gf": "RootOf(_Z^4+2*_Z^3+(2*_x+1)*_Z^2+(-1+2*_x)*_Z+_x^2)",
    "rec": "{(6144*_n^4+9216*_n^3+1152*_n^2-2496*_n-576)*_f(_n)+(-7936*_n^3-28032*_n^2-30320*_n-9096)*_f(_n+1)+(6272*_n^2+15488*_n+10404)*_f(_n+2)+(-3784*_n-7600)*_f(_n+3)+589*_f(_n+4), _f(0) = 0, _f(1) = 0, _f(2) = 2, _f(3) = 12, _f(4) = 120}",
    "equiv": "-1/2/Pi^(1/2)*RootOf(-37*RootOf(2*_Z^3+4*_Z^2+2*_Z-1,.297156508177424)^2+70*_Z^2-15*RootOf(2*_Z^3+4*_Z^2+2*_Z-1,.297156508177424)+3)*(1/_n)^(3/2)*(16/31*RootOf(2*_Z^3+4*_Z^2+2*_Z-1,.297156508177424)^2+104/31*RootOf(2*_Z^3+4*_Z^2+2*_Z-1,.297156508177424)+112/31)^(-ln(exp(-_n)))"
}