{
    "id": 83,
    "name": "Pairs of cycles",
    "description": "Pairs of cycles of cardinality at least 1",
    "specification": "{B = Cycle(Z), S = Prod(B,B)}",
    "labeled": true,
    "symbol": "S",
    "terms": [
        0,
        0,
        2,
        6,
        22,
        100,
        548,
        3528,
        26136,
        219168,
        2053152,
        21257280,
        241087680,
        2972885760,
        39605518080,
        566931294720,
        8678326003200,
        141468564787200,
        2446811181158400,
        44753976117043200,
        863130293635276800
    ],
    "references": [
        "EIS A052517"
    ],
    "gf": "ln(-1/(-1+_x))^2",
    "rec": "{(_n^2+2*_n+1)*_f(_n+1)+(-2*_n-3)*_f(_n+2)+_f(_n+3), _f(0) = 0, _f(1) = 0, _f(2) = 2, _f(3) = 6}",
    "closedform": "2*GAMMA(_n)*(Psi(_n)+gamma)",
    "equiv": "2*ln(_n)/_n"
}